<?xml version="1.0" encoding="utf-8"?>
<ode><userPreferences><userPreference><key>theme</key><value>neo</value></userPreference></userPreferences><odeResources><odeResource><key>odeVersionId</key><value>20251211135619SVJMUJ</value></odeResource><odeResource><key>odeId</key><value>20251210212053AIUDAT</value></odeResource><odeResource><key>odeVersionName</key><value>0</value></odeResource><odeResource><key>isDownload</key><value>true</value></odeResource></odeResources><odeProperties><odeProperty><key>pp_title</key><value>La pérdida de la biodiversidad y la extinción de especies</value></odeProperty><odeProperty><key>pp_lang</key><value>es</value></odeProperty><odeProperty><key>pp_author</key><value>Erika Alejandra Salinas Albito (Universidad Nacional de Loja )</value></odeProperty><odeProperty><key>license</key><value>creative commons: attribution - share alike 4.0</value></odeProperty><odeProperty><key>pp_description</key><value>Elaborar un Recurso educativo didáctico en eXeLearning para enseñar ciencias naturales en estudiantes de Educación General Básica media, con los temas de, "La pérdida de la biodiversidad y la extinción de especies". El recurso debe contener información teórica (sintetizada/ resumida) para enseñar a reconocer o diferenciar, actividades prácticas, y medir el aprendizaje (evaluación).

De acuerdo al enunciado elabore un recurso educativo didáctico, dinámico, novedoso y viable; para ello puede utilizar herramientas que se utiliza en el ciclo académico.</value></odeProperty><odeProperty><key>exportSource</key><value>true</value></odeProperty><odeProperty><key>pp_addExeLink</key><value>true</value></odeProperty><odeProperty><key>pp_exportElp</key><value>true</value></odeProperty><odeProperty><key>pp_addPagination</key><value>true</value></odeProperty><odeProperty><key>pp_addSearchBox</key><value>false</value></odeProperty><odeProperty><key>pp_addAccessibilityToolbar</key><value>true</value></odeProperty><odeProperty><key>pp_extraHeadContent</key><value/></odeProperty><odeProperty><key>footer</key><value/></odeProperty></odeProperties><odeNavStructures><odeNavStructure><odePageId>20251211135619MDFUWM</odePageId><odeParentPageId/><pageName>La pérdida de la biodiversidad y la extinción de especies</pageName><odeNavStructureOrder>1</odeNavStructureOrder><odeNavStructureProperties><odeNavStructureProperty><key>titleNode</key><value>La pérdida de la biodiversidad y la extinción de especies</value></odeNavStructureProperty><odeNavStructureProperty><key>titleHtml</key><value/></odeNavStructureProperty><odeNavStructureProperty><key>editableInPage</key><value>false</value></odeNavStructureProperty><odeNavStructureProperty><key>titlePage</key><value>La pérdida de la biodiversidad y la extinción de especies</value></odeNavStructureProperty><odeNavStructureProperty><key>visibility</key><value>true</value></odeNavStructureProperty><odeNavStructureProperty><key>description</key><value/></odeNavStructureProperty></odeNavStructureProperties><odePagStructures><odePagStructure><odePageId>20251211135619MDFUWM</odePageId><odeBlockId>20251211135619RFMILN</odeBlockId><blockName>Texto</blockName><iconName/><odePagStructureOrder>1</odePagStructureOrder><odePagStructureProperties><odePagStructureProperty><key>visibility</key><value>true</value></odePagStructureProperty><odePagStructureProperty><key>teacherOnly</key><value>false</value></odePagStructureProperty><odePagStructureProperty><key>allowToggle</key><value>true</value></odePagStructureProperty><odePagStructureProperty><key>minimized</key><value>false</value></odePagStructureProperty><odePagStructureProperty><key>identifier</key><value/></odePagStructureProperty><odePagStructureProperty><key>cssClass</key><value/></odePagStructureProperty></odePagStructureProperties><odeComponents><odeComponent><odePageId>20251211135619MDFUWM</odePageId><odeBlockId>20251211135619RFMILN</odeBlockId><odeIdeviceId>20251210170635094KB1</odeIdeviceId><odeIdeviceTypeName>text</odeIdeviceTypeName><htmlView>&lt;div class="exe-text-template"&gt;&lt;div class="textIdeviceContent"&gt;
            &lt;div class="exe-text-activity"&gt;
                &lt;div&gt;&lt;p&gt;&lt;img src="{{context_path}}/20251210170635094KB1/1_1.png" width="1024" height="576" alt=""&gt;&lt;/p&gt;&lt;p class="clearfix"&gt;&lt;/p&gt;&lt;/div&gt;
            &lt;/div&gt;&lt;/div&gt;&lt;/div&gt;</htmlView><jsonProperties>{"ideviceId":"20251210170635094KB1","textInfoDurationInput":"","textInfoDurationTextInput":"Duración","textInfoParticipantsInput":"","textInfoParticipantsTextInput":"Agrupamiento","textTextarea":"&lt;p&gt;&lt;img src=\"{{context_path}}/20251210170635094KB1/1_1.png\" width=\"1024\" height=\"576\" alt=\"\" /&gt;&lt;/p&gt;","textFeedbackInput":"Mostrar retroalimentación","textFeedbackTextarea":""}</jsonProperties><odeComponentsOrder>1</odeComponentsOrder><odeComponentsProperties><odeComponentsProperty><key>visibility</key><value>true</value></odeComponentsProperty><odeComponentsProperty><key>teacherOnly</key><value>false</value></odeComponentsProperty><odeComponentsProperty><key>identifier</key><value/></odeComponentsProperty><odeComponentsProperty><key>cssClass</key><value/></odeComponentsProperty></odeComponentsProperties></odeComponent></odeComponents></odePagStructure></odePagStructures></odeNavStructure><odeNavStructure><odePageId>20251211135619GKLAAA</odePageId><odeParentPageId>20251211135619MDFUWM</odeParentPageId><pageName>Introducción</pageName><odeNavStructureOrder>1</odeNavStructureOrder><odeNavStructureProperties><odeNavStructureProperty><key>titleNode</key><value/></odeNavStructureProperty><odeNavStructureProperty><key>titleHtml</key><value/></odeNavStructureProperty><odeNavStructureProperty><key>editableInPage</key><value>false</value></odeNavStructureProperty><odeNavStructureProperty><key>titlePage</key><value>Introducción</value></odeNavStructureProperty><odeNavStructureProperty><key>visibility</key><value>true</value></odeNavStructureProperty><odeNavStructureProperty><key>description</key><value/></odeNavStructureProperty></odeNavStructureProperties><odePagStructures><odePagStructure><odePageId>20251211135619GKLAAA</odePageId><odeBlockId>20251211135619KCEBLU</odeBlockId><blockName>Texto</blockName><iconName/><odePagStructureOrder>1</odePagStructureOrder><odePagStructureProperties><odePagStructureProperty><key>visibility</key><value>true</value></odePagStructureProperty><odePagStructureProperty><key>teacherOnly</key><value>false</value></odePagStructureProperty><odePagStructureProperty><key>allowToggle</key><value>true</value></odePagStructureProperty><odePagStructureProperty><key>minimized</key><value>false</value></odePagStructureProperty><odePagStructureProperty><key>identifier</key><value/></odePagStructureProperty><odePagStructureProperty><key>cssClass</key><value/></odePagStructureProperty></odePagStructureProperties><odeComponents><odeComponent><odePageId>20251211135619GKLAAA</odePageId><odeBlockId>20251211135619KCEBLU</odeBlockId><odeIdeviceId>20251210170844091YIZ</odeIdeviceId><odeIdeviceTypeName>text</odeIdeviceTypeName><htmlView>&lt;div class="exe-text-template"&gt;&lt;div class="textIdeviceContent"&gt;
            &lt;div class="exe-text-activity"&gt;
                &lt;div&gt;&lt;p&gt;&lt;img src="{{context_path}}/20251210170844091YIZ/2.png" width="1024" height="576" alt=""&gt;&lt;/p&gt;&lt;p class="clearfix"&gt;&lt;/p&gt;&lt;/div&gt;
            &lt;/div&gt;&lt;/div&gt;&lt;/div&gt;</htmlView><jsonProperties>{"ideviceId":"20251210170844091YIZ","textInfoDurationInput":"","textInfoDurationTextInput":"Duración","textInfoParticipantsInput":"","textInfoParticipantsTextInput":"Agrupamiento","textTextarea":"&lt;p&gt;&lt;img src=\"{{context_path}}/20251210170844091YIZ/2.png\" width=\"1024\" height=\"576\" alt=\"\" /&gt;&lt;/p&gt;","textFeedbackInput":"Mostrar retroalimentación","textFeedbackTextarea":""}</jsonProperties><odeComponentsOrder>1</odeComponentsOrder><odeComponentsProperties><odeComponentsProperty><key>visibility</key><value>true</value></odeComponentsProperty><odeComponentsProperty><key>teacherOnly</key><value>false</value></odeComponentsProperty><odeComponentsProperty><key>identifier</key><value/></odeComponentsProperty><odeComponentsProperty><key>cssClass</key><value/></odeComponentsProperty></odeComponentsProperties></odeComponent></odeComponents></odePagStructure></odePagStructures></odeNavStructure><odeNavStructure><odePageId>20251211135619SLRSHF</odePageId><odeParentPageId>20251211135619GKLAAA</odeParentPageId><pageName>Contenido Teórico Sintetizado</pageName><odeNavStructureOrder>1</odeNavStructureOrder><odeNavStructureProperties><odeNavStructureProperty><key>titleNode</key><value/></odeNavStructureProperty><odeNavStructureProperty><key>titleHtml</key><value/></odeNavStructureProperty><odeNavStructureProperty><key>editableInPage</key><value>false</value></odeNavStructureProperty><odeNavStructureProperty><key>titlePage</key><value>Contenido Teórico Sintetizado</value></odeNavStructureProperty><odeNavStructureProperty><key>visibility</key><value>true</value></odeNavStructureProperty><odeNavStructureProperty><key>description</key><value/></odeNavStructureProperty></odeNavStructureProperties><odePagStructures><odePagStructure><odePageId>20251211135619SLRSHF</odePageId><odeBlockId>20251211135619GJTYVM</odeBlockId><blockName>Texto</blockName><iconName/><odePagStructureOrder>1</odePagStructureOrder><odePagStructureProperties><odePagStructureProperty><key>visibility</key><value>true</value></odePagStructureProperty><odePagStructureProperty><key>teacherOnly</key><value>false</value></odePagStructureProperty><odePagStructureProperty><key>allowToggle</key><value>true</value></odePagStructureProperty><odePagStructureProperty><key>minimized</key><value>false</value></odePagStructureProperty><odePagStructureProperty><key>identifier</key><value/></odePagStructureProperty><odePagStructureProperty><key>cssClass</key><value/></odePagStructureProperty></odePagStructureProperties><odeComponents><odeComponent><odePageId>20251211135619SLRSHF</odePageId><odeBlockId>20251211135619GJTYVM</odeBlockId><odeIdeviceId>2025121017090690858D</odeIdeviceId><odeIdeviceTypeName>text</odeIdeviceTypeName><htmlView>&lt;div class="exe-text-template"&gt;&lt;div class="textIdeviceContent"&gt;
            &lt;div class="exe-text-activity"&gt;
                &lt;div&gt;&lt;p&gt;&lt;img src="{{context_path}}/2025121017090690858D/3.png" width="1024" height="576" alt=""&gt;&lt;/p&gt;&lt;p class="clearfix"&gt;&lt;/p&gt;&lt;/div&gt;
            &lt;/div&gt;&lt;/div&gt;&lt;/div&gt;</htmlView><jsonProperties>{"ideviceId":"2025121017090690858D","textInfoDurationInput":"","textInfoDurationTextInput":"Duración","textInfoParticipantsInput":"","textInfoParticipantsTextInput":"Agrupamiento","textTextarea":"&lt;p&gt;&lt;img src=\"{{context_path}}/2025121017090690858D/3.png\" width=\"1024\" height=\"576\" alt=\"\" /&gt;&lt;/p&gt;","textFeedbackInput":"Mostrar retroalimentación","textFeedbackTextarea":""}</jsonProperties><odeComponentsOrder>1</odeComponentsOrder><odeComponentsProperties><odeComponentsProperty><key>visibility</key><value>true</value></odeComponentsProperty><odeComponentsProperty><key>teacherOnly</key><value>false</value></odeComponentsProperty><odeComponentsProperty><key>identifier</key><value/></odeComponentsProperty><odeComponentsProperty><key>cssClass</key><value/></odeComponentsProperty></odeComponentsProperties></odeComponent></odeComponents></odePagStructure></odePagStructures></odeNavStructure><odeNavStructure><odePageId>20251211135619PWCICL</odePageId><odeParentPageId>20251211135619SLRSHF</odeParentPageId><pageName>Importancia de la biodiversidad</pageName><odeNavStructureOrder>1</odeNavStructureOrder><odeNavStructureProperties><odeNavStructureProperty><key>titleNode</key><value>Importancia de la biodiversidad</value></odeNavStructureProperty><odeNavStructureProperty><key>titleHtml</key><value/></odeNavStructureProperty><odeNavStructureProperty><key>editableInPage</key><value>false</value></odeNavStructureProperty><odeNavStructureProperty><key>titlePage</key><value>Importancia de la biodiversidad</value></odeNavStructureProperty><odeNavStructureProperty><key>visibility</key><value>true</value></odeNavStructureProperty><odeNavStructureProperty><key>description</key><value/></odeNavStructureProperty></odeNavStructureProperties><odePagStructures><odePagStructure><odePageId>20251211135619PWCICL</odePageId><odeBlockId>20251211135619UEMUET</odeBlockId><blockName>Texto</blockName><iconName/><odePagStructureOrder>1</odePagStructureOrder><odePagStructureProperties><odePagStructureProperty><key>visibility</key><value>true</value></odePagStructureProperty><odePagStructureProperty><key>teacherOnly</key><value>false</value></odePagStructureProperty><odePagStructureProperty><key>allowToggle</key><value>true</value></odePagStructureProperty><odePagStructureProperty><key>minimized</key><value>false</value></odePagStructureProperty><odePagStructureProperty><key>identifier</key><value/></odePagStructureProperty><odePagStructureProperty><key>cssClass</key><value/></odePagStructureProperty></odePagStructureProperties><odeComponents><odeComponent><odePageId>20251211135619PWCICL</odePageId><odeBlockId>20251211135619UEMUET</odeBlockId><odeIdeviceId>20251210170954077UXE</odeIdeviceId><odeIdeviceTypeName>text</odeIdeviceTypeName><htmlView>&lt;div class="exe-text-template"&gt;&lt;div class="textIdeviceContent"&gt;
            &lt;div class="exe-text-activity"&gt;
                &lt;div&gt;&lt;p&gt;&lt;img src="{{context_path}}/20251210170954077UXE/4.png" width="1024" height="576" alt=""&gt;&lt;/p&gt;&lt;p class="clearfix"&gt;&lt;/p&gt;&lt;/div&gt;
            &lt;/div&gt;&lt;/div&gt;&lt;/div&gt;</htmlView><jsonProperties>{"ideviceId":"20251210170954077UXE","textInfoDurationInput":"","textInfoDurationTextInput":"Duración","textInfoParticipantsInput":"","textInfoParticipantsTextInput":"Agrupamiento","textTextarea":"&lt;p&gt;&lt;img src=\"{{context_path}}/20251210170954077UXE/4.png\" width=\"1024\" height=\"576\" alt=\"\" /&gt;&lt;/p&gt;","textFeedbackInput":"Mostrar retroalimentación","textFeedbackTextarea":""}</jsonProperties><odeComponentsOrder>1</odeComponentsOrder><odeComponentsProperties><odeComponentsProperty><key>visibility</key><value>true</value></odeComponentsProperty><odeComponentsProperty><key>teacherOnly</key><value>false</value></odeComponentsProperty><odeComponentsProperty><key>identifier</key><value/></odeComponentsProperty><odeComponentsProperty><key>cssClass</key><value/></odeComponentsProperty></odeComponentsProperties></odeComponent></odeComponents></odePagStructure></odePagStructures></odeNavStructure><odeNavStructure><odePageId>20251211135619OFPQGW</odePageId><odeParentPageId>20251211135619PWCICL</odeParentPageId><pageName>¿Qué es la pérdida de biodiversidad?</pageName><odeNavStructureOrder>1</odeNavStructureOrder><odeNavStructureProperties><odeNavStructureProperty><key>titleNode</key><value>¿Qué es la pérdida de biodiversidad?</value></odeNavStructureProperty><odeNavStructureProperty><key>titleHtml</key><value/></odeNavStructureProperty><odeNavStructureProperty><key>editableInPage</key><value>false</value></odeNavStructureProperty><odeNavStructureProperty><key>titlePage</key><value>¿Qué es la pérdida de biodiversidad?</value></odeNavStructureProperty><odeNavStructureProperty><key>visibility</key><value>true</value></odeNavStructureProperty><odeNavStructureProperty><key>description</key><value/></odeNavStructureProperty></odeNavStructureProperties><odePagStructures><odePagStructure><odePageId>20251211135619OFPQGW</odePageId><odeBlockId>20251211135619UVOMQT</odeBlockId><blockName>Texto</blockName><iconName/><odePagStructureOrder>1</odePagStructureOrder><odePagStructureProperties><odePagStructureProperty><key>visibility</key><value>true</value></odePagStructureProperty><odePagStructureProperty><key>teacherOnly</key><value>false</value></odePagStructureProperty><odePagStructureProperty><key>allowToggle</key><value>true</value></odePagStructureProperty><odePagStructureProperty><key>minimized</key><value>false</value></odePagStructureProperty><odePagStructureProperty><key>identifier</key><value/></odePagStructureProperty><odePagStructureProperty><key>cssClass</key><value/></odePagStructureProperty></odePagStructureProperties><odeComponents><odeComponent><odePageId>20251211135619OFPQGW</odePageId><odeBlockId>20251211135619UVOMQT</odeBlockId><odeIdeviceId>20251210171037311L5A</odeIdeviceId><odeIdeviceTypeName>text</odeIdeviceTypeName><htmlView>&lt;div class="exe-text-template"&gt;&lt;div class="textIdeviceContent"&gt;
            &lt;div class="exe-text-activity"&gt;
                &lt;div&gt;&lt;p&gt;&lt;img src="{{context_path}}/20251210171037311L5A/6.png" width="1024" height="576" alt=""&gt;&lt;/p&gt;&lt;p class="clearfix"&gt;&lt;/p&gt;&lt;/div&gt;
            &lt;/div&gt;&lt;/div&gt;&lt;/div&gt;</htmlView><jsonProperties>{"ideviceId":"20251210171037311L5A","textInfoDurationInput":"","textInfoDurationTextInput":"Duración","textInfoParticipantsInput":"","textInfoParticipantsTextInput":"Agrupamiento","textTextarea":"&lt;p&gt;&lt;img src=\"{{context_path}}/20251210171037311L5A/6.png\" width=\"1024\" height=\"576\" alt=\"\" /&gt;&lt;/p&gt;","textFeedbackInput":"Mostrar retroalimentación","textFeedbackTextarea":""}</jsonProperties><odeComponentsOrder>1</odeComponentsOrder><odeComponentsProperties><odeComponentsProperty><key>visibility</key><value>true</value></odeComponentsProperty><odeComponentsProperty><key>teacherOnly</key><value>false</value></odeComponentsProperty><odeComponentsProperty><key>identifier</key><value/></odeComponentsProperty><odeComponentsProperty><key>cssClass</key><value/></odeComponentsProperty></odeComponentsProperties></odeComponent></odeComponents></odePagStructure><odePagStructure><odePageId>20251211135619OFPQGW</odePageId><odeBlockId>20251211135619MQXCRO</odeBlockId><blockName>Texto</blockName><iconName/><odePagStructureOrder>2</odePagStructureOrder><odePagStructureProperties><odePagStructureProperty><key>visibility</key><value>true</value></odePagStructureProperty><odePagStructureProperty><key>teacherOnly</key><value>false</value></odePagStructureProperty><odePagStructureProperty><key>allowToggle</key><value>true</value></odePagStructureProperty><odePagStructureProperty><key>minimized</key><value>false</value></odePagStructureProperty><odePagStructureProperty><key>identifier</key><value/></odePagStructureProperty><odePagStructureProperty><key>cssClass</key><value/></odePagStructureProperty></odePagStructureProperties><odeComponents><odeComponent><odePageId>20251211135619OFPQGW</odePageId><odeBlockId>20251211135619MQXCRO</odeBlockId><odeIdeviceId>202512101720039079L6</odeIdeviceId><odeIdeviceTypeName>text</odeIdeviceTypeName><htmlView>&lt;div class="exe-text-template"&gt;&lt;div class="textIdeviceContent"&gt;
            &lt;div class="exe-text-activity"&gt;
                &lt;div&gt;&lt;p&gt;&lt;img src="{{context_path}}/202512101720039079L6/6.png" width="1024" height="669" alt="MUERCOLES "&gt;&lt;/p&gt;&lt;p class="clearfix"&gt;&lt;/p&gt;&lt;/div&gt;
            &lt;/div&gt;&lt;/div&gt;&lt;/div&gt;</htmlView><jsonProperties>{"ideviceId":"202512101720039079L6","textInfoDurationInput":"","textInfoDurationTextInput":"Duración","textInfoParticipantsInput":"","textInfoParticipantsTextInput":"Agrupamiento","textTextarea":"&lt;p&gt;&lt;img src=\"{{context_path}}/202512101720039079L6/6.png\" width=\"1024\" height=\"669\" alt=\"MUERCOLES \" /&gt;&lt;/p&gt;","textFeedbackInput":"Mostrar retroalimentación","textFeedbackTextarea":""}</jsonProperties><odeComponentsOrder>1</odeComponentsOrder><odeComponentsProperties><odeComponentsProperty><key>visibility</key><value>true</value></odeComponentsProperty><odeComponentsProperty><key>teacherOnly</key><value>false</value></odeComponentsProperty><odeComponentsProperty><key>identifier</key><value/></odeComponentsProperty><odeComponentsProperty><key>cssClass</key><value/></odeComponentsProperty></odeComponentsProperties></odeComponent></odeComponents></odePagStructure></odePagStructures></odeNavStructure><odeNavStructure><odePageId>20251211135619DOENMI</odePageId><odeParentPageId>20251211135619OFPQGW</odeParentPageId><pageName>Extinción de especies</pageName><odeNavStructureOrder>1</odeNavStructureOrder><odeNavStructureProperties><odeNavStructureProperty><key>titleNode</key><value>Extinción de especies</value></odeNavStructureProperty><odeNavStructureProperty><key>titleHtml</key><value/></odeNavStructureProperty><odeNavStructureProperty><key>editableInPage</key><value>false</value></odeNavStructureProperty><odeNavStructureProperty><key>titlePage</key><value>Extinción de especies</value></odeNavStructureProperty><odeNavStructureProperty><key>visibility</key><value>true</value></odeNavStructureProperty><odeNavStructureProperty><key>description</key><value/></odeNavStructureProperty></odeNavStructureProperties><odePagStructures><odePagStructure><odePageId>20251211135619DOENMI</odePageId><odeBlockId>20251211135619GWHUBR</odeBlockId><blockName>Texto</blockName><iconName/><odePagStructureOrder>1</odePagStructureOrder><odePagStructureProperties><odePagStructureProperty><key>visibility</key><value>true</value></odePagStructureProperty><odePagStructureProperty><key>teacherOnly</key><value>false</value></odePagStructureProperty><odePagStructureProperty><key>allowToggle</key><value>true</value></odePagStructureProperty><odePagStructureProperty><key>minimized</key><value>false</value></odePagStructureProperty><odePagStructureProperty><key>identifier</key><value/></odePagStructureProperty><odePagStructureProperty><key>cssClass</key><value/></odePagStructureProperty></odePagStructureProperties><odeComponents><odeComponent><odePageId>20251211135619DOENMI</odePageId><odeBlockId>20251211135619GWHUBR</odeBlockId><odeIdeviceId>2025121017192762062P</odeIdeviceId><odeIdeviceTypeName>text</odeIdeviceTypeName><htmlView>&lt;div class="exe-text-template"&gt;&lt;div class="textIdeviceContent"&gt;
            &lt;div class="exe-text-activity"&gt;
                &lt;div&gt;&lt;p&gt;&lt;img src="{{context_path}}/2025121017192762062P/7.png" width="1024" height="576" alt="LUNES "&gt;&lt;/p&gt;&lt;p class="clearfix"&gt;&lt;/p&gt;&lt;/div&gt;
            &lt;/div&gt;&lt;/div&gt;&lt;/div&gt;</htmlView><jsonProperties>{"ideviceId":"2025121017192762062P","textInfoDurationInput":"","textInfoDurationTextInput":"Duración","textInfoParticipantsInput":"","textInfoParticipantsTextInput":"Agrupamiento","textTextarea":"&lt;p&gt;&lt;img src=\"{{context_path}}/2025121017192762062P/7.png\" width=\"1024\" height=\"576\" alt=\"LUNES \" /&gt;&lt;/p&gt;","textFeedbackInput":"Mostrar retroalimentación","textFeedbackTextarea":""}</jsonProperties><odeComponentsOrder>1</odeComponentsOrder><odeComponentsProperties><odeComponentsProperty><key>visibility</key><value>true</value></odeComponentsProperty><odeComponentsProperty><key>teacherOnly</key><value>false</value></odeComponentsProperty><odeComponentsProperty><key>identifier</key><value/></odeComponentsProperty><odeComponentsProperty><key>cssClass</key><value/></odeComponentsProperty></odeComponentsProperties></odeComponent></odeComponents></odePagStructure></odePagStructures></odeNavStructure><odeNavStructure><odePageId>20251211135619EKJKRK</odePageId><odeParentPageId>20251211135619DOENMI</odeParentPageId><pageName>Actividades Prácticas</pageName><odeNavStructureOrder>1</odeNavStructureOrder><odeNavStructureProperties><odeNavStructureProperty><key>titleNode</key><value/></odeNavStructureProperty><odeNavStructureProperty><key>titleHtml</key><value/></odeNavStructureProperty><odeNavStructureProperty><key>editableInPage</key><value>false</value></odeNavStructureProperty><odeNavStructureProperty><key>titlePage</key><value>Actividades Prácticas</value></odeNavStructureProperty><odeNavStructureProperty><key>visibility</key><value>true</value></odeNavStructureProperty><odeNavStructureProperty><key>description</key><value/></odeNavStructureProperty></odeNavStructureProperties><odePagStructures><odePagStructure><odePageId>20251211135619EKJKRK</odePageId><odeBlockId>20251211135619LWRXZA</odeBlockId><blockName>Verdadero o falso</blockName><iconName/><odePagStructureOrder>1</odePagStructureOrder><odePagStructureProperties><odePagStructureProperty><key>visibility</key><value>true</value></odePagStructureProperty><odePagStructureProperty><key>teacherOnly</key><value>false</value></odePagStructureProperty><odePagStructureProperty><key>allowToggle</key><value>true</value></odePagStructureProperty><odePagStructureProperty><key>minimized</key><value>false</value></odePagStructureProperty><odePagStructureProperty><key>identifier</key><value/></odePagStructureProperty><odePagStructureProperty><key>cssClass</key><value/></odePagStructureProperty></odePagStructureProperties><odeComponents><odeComponent><odePageId>20251211135619EKJKRK</odePageId><odeBlockId>20251211135619LWRXZA</odeBlockId><odeIdeviceId>20251210172124191YDZ</odeIdeviceId><odeIdeviceTypeName>trueorfalse</odeIdeviceTypeName><htmlView>&lt;div class="exe-trueorfalse-container"&gt;
    &lt;div class="game-evaluation-ids js-hidden" data-id="20251210172124191YDZ" data-evaluationb="false" data-evaluationid="20251210212053AIUDAT"&gt;&lt;/div&gt;
        &lt;div class="TOFP-instructions"&gt;&lt;p&gt;Responde todas las preguntas del cuestionario.&lt;/p&gt;&lt;/div&gt;
        &lt;div class="TOFP-MainContainer" data-instance="20251210172124191YDZ" id="tofPMainContainer-20251210172124191YDZ"&gt;
            &lt;div class="TOFP-GameContainer" id="tofPGameContainer-20251210172124191YDZ"&gt;
                &lt;div class="TOFP-GameScoreBoard TOFP-EHidden"&gt;
                    &lt;div class="TOFP-TimeNumber"&gt;
                        &lt;strong&gt;&lt;span class="sr-av"&gt;Tiempo por pregunta:&lt;/span&gt;&lt;/strong&gt;
                        &lt;p id="tofPPTime-20251210172124191YDZ" class="TOFP-PTime"&gt;00:00:&lt;/p&gt;
                    &lt;/div&gt;
                &lt;/div&gt;
                &lt;div class="TOFP-MessgeDiv" id="tofPMessageDiv-20251210172124191YDZ"&gt;
                    &lt;div class="TOFP-Message" id="tofPMessage-20251210172124191YDZ"&gt;&lt;/div&gt;
                &lt;/div&gt;
                &lt;div class="TOFP-StartGameDiv TOFP-EHidden" id="tofPStartGameDiv-20251210172124191YDZ"&gt;
                    &lt;button  id="tofPStartGame-20251210172124191YDZ" type="button" class="btn btn-primary"&gt;Pulse aquí para empezar&lt;/button&gt;
                &lt;/div&gt;
                &lt;div class="TOFP-Multimedia " id="tofPMultimedia-20251210172124191YDZ"&gt;
                &lt;/div&gt;
                &lt;div class="TOFP-CheckTestDiv TOFP-EHidden" id="tofPCheckTestDiv-20251210172124191YDZ"&gt;
                    &lt;button id="tofPCheckTest-20251210172124191YDZ" type="button" class="btn btn-primary"&gt;Comprobar&lt;/button&gt;
                    &lt;button id="tofRebootTest-20251210172124191YDZ" type="button" class="btn btn-primary TOFP-EHidden"&gt;¡Prueba otra vez!&lt;/button&gt;
                &lt;/div&gt;
        &lt;/div&gt; 
        &lt;div class="Games-BottonContainer"&gt;
            &lt;div class="Games-GetScore"&gt;
                &lt;input id="tofPSendScore-20251210172124191YDZ" type="button" value="Guardar la puntuación" class="feedbackbutton Games-SendScore" style="display:none"/&gt; &lt;span class="Games-RepeatActivity"&gt;&lt;/span&gt;
            &lt;/div&gt;
        &lt;/div&gt;
        &lt;div class="TOFP-After"&gt;&lt;/div&gt;
        &lt;div class="questionsMedia" style="display:none"&gt;&lt;/div&gt;&lt;/div&gt;</htmlView><jsonProperties>{"id":"20251210172124191YDZ","typeGame":"TrueOrFalse","eXeGameInstructions":"&lt;p&gt;Responde todas las preguntas del cuestionario.&lt;/p&gt;","eXeIdeviceTextAfter":"","msgs":{"msgStartGame":"Pulse aquí para empezar","msgTime":"Tiempo por pregunta","msgNoImage":"Pregunta sin imágenes","msgScoreScorm":"La puntuación no se puede guardar porque esta página no forma parte  de un paquete SCORM.","msgEndGameScore":"Antes de guardar la puntuación comience la partida.","msgOnlySaveScore":"¡Solo puede guardar la puntuación una vez!","msgOnlySave":"Solo puede guardar una vez","msgYouScore":"Su puntuación","msgAuthor":"Autoría","msgOnlySaveAuto":"Su puntuación se guardará después de cada pregunta. Solo puede jugar una vez.","msgSaveAuto":"Su puntuación se guardará automáticamente después de cada pregunta.","msgSeveralScore":"Puede guardar la puntuación tantas veces como quiera","msgYouLastScore":"La última puntuación guardada es","msgActityComply":"Ya ha realizado esta actividad.","msgPlaySeveralTimes":"Puede realizar esta actividad cuantas veces quiera","msgUncompletedActivity":"Actividad no completada","msgSuccessfulActivity":"Actividad superada. Puntuación: %s","msgUnsuccessfulActivity":"Actividad no superada. Puntuación: %s","msgTypeGame":"Verdadero o falso","msgFeedback":"Retroalimentación","msgSuggestion":"Sugerencia","msgSolution":"Solución","msgQuestion":"Pregunta","msgTrue":"Verdadero","msgFalse":"Falso","msgOk":"Correcto","msgKO":"Incorrecto","msgShow":"Mostrar","msgHide":"Ocultar","msgCheck":"Comprobar","msgReboot":"¡Prueba otra vez!","msgScore":"Puntuación","msgWeight":"Peso","msgNext":"Siguiente","msgPrevious":"Anterior"},"questionsRandom":false,"percentageQuestions":100,"isTest":false,"time":0,"questionsGame":[{"question":"&lt;p&gt;“La contaminación del agua no afecta a la biodiversidad.”&lt;br /&gt;&lt;/p&gt;","feedback":"&lt;p&gt; Sí afecta y puede causar la muerte de muchas especies.&lt;/p&gt;","suggestion":"","solution":0}],"isScorm":0,"textButtonScorm":"Guardar la puntuación","repeatActivity":true,"weighted":100,"evaluation":false,"evaluationID":"20251210212053AIUDAT","showSlider":false,"ideviceId":"20251210172124191YDZ"}</jsonProperties><odeComponentsOrder>1</odeComponentsOrder><odeComponentsProperties><odeComponentsProperty><key>visibility</key><value>true</value></odeComponentsProperty><odeComponentsProperty><key>teacherOnly</key><value>false</value></odeComponentsProperty><odeComponentsProperty><key>identifier</key><value/></odeComponentsProperty><odeComponentsProperty><key>cssClass</key><value/></odeComponentsProperty></odeComponentsProperties></odeComponent></odeComponents></odePagStructure><odePagStructure><odePageId>20251211135619EKJKRK</odePageId><odeBlockId>20251211135619EJMGDU</odeBlockId><blockName>Relaciona</blockName><iconName/><odePagStructureOrder>2</odePagStructureOrder><odePagStructureProperties><odePagStructureProperty><key>visibility</key><value>true</value></odePagStructureProperty><odePagStructureProperty><key>teacherOnly</key><value>false</value></odePagStructureProperty><odePagStructureProperty><key>allowToggle</key><value>true</value></odePagStructureProperty><odePagStructureProperty><key>minimized</key><value>false</value></odePagStructureProperty><odePagStructureProperty><key>identifier</key><value/></odePagStructureProperty><odePagStructureProperty><key>cssClass</key><value/></odePagStructureProperty></odePagStructureProperties><odeComponents><odeComponent><odePageId>20251211135619EKJKRK</odePageId><odeBlockId>20251211135619EJMGDU</odeBlockId><odeIdeviceId>202512101725308224ED</odeIdeviceId><odeIdeviceTypeName>relate</odeIdeviceTypeName><htmlView>&lt;div class="relaciona-IDevice"&gt;&lt;div class="relaciona-instructions gameQP-instructions"&gt;&lt;p&gt;&lt;strong&gt;Relaciona cada causa con el efecto correspondiente.&lt;/strong&gt;&lt;/p&gt;
&lt;p&gt; &lt;/p&gt;&lt;/div&gt;&lt;div class="relaciona-DataGame js-hidden"&gt;{"typeGame":"Relaciona","author":"","randomCards":true,"instructions":"&lt;p&gt;&lt;strong&gt;Relaciona cada causa con el efecto correspondiente.&lt;/strong&gt;&lt;/p&gt;\n&lt;p&gt; &lt;/p&gt;","showMinimize":false,"itinerary":{"showClue":false,"clueGame":"","percentageClue":40,"showCodeAccess":false,"codeAccess":"","messageCodeAccess":""},"cardsGame":[{"url":"","x":0,"y":0,"author":"","alt":"","audio":"","color":"#000000","backcolor":"#ffffff","eText":"Deforestaci%C3%B3n","urlBk":"","xBk":0,"yBk":0,"authorBk":"","altBk":"","audioBk":"","colorBk":"#000000","backcolorBk":"#ffffff","eTextBk":"P%C3%A9rdida%20del%20h%C3%A1bitat%20de%20muchas%20especies"},{"url":"","x":0,"y":0,"author":"","alt":"","audio":"","color":"#000000","backcolor":"#ffffff","eText":"Contaminaci%C3%B3n%20del%20agua","urlBk":"","xBk":0,"yBk":0,"authorBk":"","altBk":"","audioBk":"","colorBk":"#000000","backcolorBk":"#ffffff","eTextBk":"Muerte%20de%20peces%20y%20alteraci%C3%B3n%20de%20ecosistemas%20acu%C3%A1ticos"},{"url":"","x":0,"y":0,"author":"","alt":"","audio":"","color":"#000000","backcolor":"#ffffff","eText":"Cambio%20clim%C3%A1tico","urlBk":"","xBk":0,"yBk":0,"authorBk":"","altBk":"","audioBk":"","colorBk":"#000000","backcolorBk":"#ffffff","eTextBk":"Alteraci%C3%B3n%20de%20temperaturas%20y%20desaparici%C3%B3n%20de%20ecosistemas"},{"url":"","x":0,"y":0,"author":"","alt":"","audio":"","color":"#000000","backcolor":"#ffffff","eText":"Caza%20ilegal","urlBk":"","xBk":0,"yBk":0,"authorBk":"","altBk":"","audioBk":"","colorBk":"#000000","backcolorBk":"#ffffff","eTextBk":"Disminuci%C3%B3n%20acelerada%20de%20animales%20en%20peligro"},{"url":"","x":0,"y":0,"author":"","alt":"","audio":"","color":"#000000","backcolor":"#ffffff","eText":"Especies%20invasoras","urlBk":"","xBk":0,"yBk":0,"authorBk":"","altBk":"","audioBk":"","colorBk":"#000000","backcolorBk":"#ffffff","eTextBk":"Desplazan%20a%20las%20especies%20nativas"}],"isScorm":0,"textButtonScorm":"Guardar la puntuación","repeatActivity":true,"weighted":100,"textAfter":"","version":2,"percentajeCards":100,"type":1,"showSolution":true,"timeShowSolution":3,"time":3,"evaluation":false,"evaluationID":"20251210212053AIUDAT","id":"202512101725308224ED","msgs":{"msgSubmit":"Enviar","msgClue":"¡Genial! La pista es:","msgCodeAccess":"Código de acceso","msgPlayStart":"Pulse aquí para jugar","msgScore":"Puntuación","msgErrors":"Errores","msgHits":"Aciertos","msgMinimize":"Minimizar","msgMaximize":"Maximizar","msgFullScreen":"Pantalla Completa","msgExitFullScreen":"Salir del modo pantalla completa","msgNoImage":"Pregunta sin imágenes","msgEndGameScore":"Antes de guardar la puntuación comience la partida.","msgScoreScorm":"La puntuación no se puede guardar porque esta página no forma parte  de un paquete SCORM.","msgOnlySaveScore":"¡Solo puede guardar la puntuación una vez!","msgOnlySave":"Solo puede guardar una vez","msgInformation":"Información","msgYouScore":"Su puntuación","msgAuthor":"Autoría","msgOnlySaveAuto":"Su puntuación se guardará después de cada pregunta. Solo puede jugar una vez.","msgSaveAuto":"Su puntuación se guardará automáticamente después de cada pregunta.","msgSeveralScore":"Puede guardar la puntuación tantas veces como quiera","msgYouLastScore":"La última puntuación guardada es","msgActityComply":"Ya ha realizado esta actividad.","msgPlaySeveralTimes":"Puede realizar esta actividad cuantas veces quiera","msgClose":"Cerrar","msgAudio":"Audio","msgNumQuestions":"Número de tarjetas","msgTryAgain":"Necesitas al menos %s% de respuestas correctas para obtener la información. Inténtalo de nuevo.","msgEndGameM":"Has completado el juego. Tu puntuación es %s.","msgUncompletedActivity":"Actividad no completada","msgSuccessfulActivity":"Actividad superada. Puntuación: %s","msgUnsuccessfulActivity":"Actividad no superada. Puntuación: %s","msgTypeGame":"Relaciona","msgCheck":"Comprobar","msgRestart":"Reiniciar"}}&lt;/div&gt;&lt;div class="game-evaluation-ids js-hidden" data-id="202512101725308224ED" data-evaluationb="false" data-evaluationid="20251210212053AIUDAT"&gt;&lt;/div&gt;&lt;div class="relaciona-bns js-hidden"&gt;Su navegador no es compatible con esta herramienta.&lt;/div&gt;&lt;/div&gt;</htmlView><jsonProperties/><odeComponentsOrder>1</odeComponentsOrder><odeComponentsProperties><odeComponentsProperty><key>visibility</key><value>true</value></odeComponentsProperty><odeComponentsProperty><key>teacherOnly</key><value>false</value></odeComponentsProperty><odeComponentsProperty><key>identifier</key><value/></odeComponentsProperty><odeComponentsProperty><key>cssClass</key><value/></odeComponentsProperty></odeComponentsProperties></odeComponent></odeComponents></odePagStructure><odePagStructure><odePageId>20251211135619EKJKRK</odePageId><odeBlockId>20251211135619RLOTPX</odeBlockId><blockName>Arrastra</blockName><iconName/><odePagStructureOrder>3</odePagStructureOrder><odePagStructureProperties><odePagStructureProperty><key>visibility</key><value>true</value></odePagStructureProperty><odePagStructureProperty><key>teacherOnly</key><value>false</value></odePagStructureProperty><odePagStructureProperty><key>allowToggle</key><value>true</value></odePagStructureProperty><odePagStructureProperty><key>minimized</key><value>false</value></odePagStructureProperty><odePagStructureProperty><key>identifier</key><value/></odePagStructureProperty><odePagStructureProperty><key>cssClass</key><value/></odePagStructureProperty></odePagStructureProperties><odeComponents><odeComponent><odePageId>20251211135619EKJKRK</odePageId><odeBlockId>20251211135619RLOTPX</odeBlockId><odeIdeviceId>20251210172744694JD6</odeIdeviceId><odeIdeviceTypeName>dragdrop</odeIdeviceTypeName><htmlView>&lt;div class="dragdrop-IDevice"&gt;&lt;div class="game-evaluation-ids js-hidden" data-id="20251210172744694JD6" data-evaluationb="false" data-evaluationid="20251210212053AIUDAT"&gt;&lt;/div&gt;&lt;div class="dragdrop-instructions gameQP-instructions"&gt;&lt;p&gt;Arrastra cada elemento al que corresponda&lt;/p&gt;&lt;/div&gt;&lt;div class="dragdrop-DataGame js-hidden"&gt;{"typeGame":"dragdrop","author":"","randomCards":true,"instructions":"&lt;p&gt;Arrastra cada elemento al que corresponda&lt;/p&gt;","showMinimize":false,"itinerary":{"showClue":false,"clueGame":"","percentageClue":40,"showCodeAccess":false,"codeAccess":"","messageCodeAccess":""},"cardsGame":[{"definition":"Deforestación","url":"{{context_path}}/20251210172744694JD6//deforestacion.png","author":"","alt":"","audio":""},{"definition":"Contaminación","url":"{{context_path}}/20251210172744694JD6//contaminacion.png","author":"","alt":"","audio":""},{"definition":"Pesca excesiva","url":"{{context_path}}/20251210172744694JD6//pesca_exesiva.png","author":"","alt":"","audio":""},{"definition":"Urbanización","url":"{{context_path}}/20251210172744694JD6//urbanizacion.png","author":"","alt":"","audio":""}],"isScorm":0,"textButtonScorm":"Guardar la puntuación","repeatActivity":true,"weighted":100,"textAfter":"","version":2,"percentajeCards":100,"type":1,"mode":1,"typeDrag":0,"showSolution":true,"timeShowSolution":3,"time":3,"evaluation":false,"evaluationID":"20251210212053AIUDAT","id":"20251210172744694JD6","msgs":{"msgSubmit":"Enviar","msgClue":"¡Genial! La pista es:","msgCodeAccess":"Código de acceso","msgPlayStart":"Pulse aquí para jugar","msgScore":"Puntuación","msgWeight":"Peso","msgErrors":"Errores","msgHits":"Aciertos","msgMinimize":"Minimizar","msgMaximize":"Maximizar","msgFullScreen":"Pantalla Completa","msgExitFullScreen":"Salir del modo pantalla completa","msgNoImage":"Pregunta sin imágenes","msgEndGameScore":"Antes de guardar la puntuación comience la partida.","msgScoreScorm":"La puntuación no se puede guardar porque esta página no forma parte  de un paquete SCORM.","msgOnlySaveScore":"¡Solo puede guardar la puntuación una vez!","msgOnlySave":"Solo puede guardar una vez","msgInformation":"Información","msgYouScore":"Su puntuación","msgAuthor":"Autoría","msgOnlySaveAuto":"Su puntuación se guardará después de cada pregunta. Solo puede jugar una vez.","msgSaveAuto":"Su puntuación se guardará automáticamente después de cada pregunta.","msgSeveralScore":"Puede guardar la puntuación tantas veces como quiera","msgYouLastScore":"La última puntuación guardada es","msgActityComply":"Ya ha realizado esta actividad.","msgPlaySeveralTimes":"Puede realizar esta actividad cuantas veces quiera","msgClose":"Cerrar","msgAudio":"Audio","msgNumQuestions":"Número de tarjetas","msgTryAgain":"Necesitas al menos %s% de respuestas correctas para obtener la información. Inténtalo de nuevo.","msgEndGameM":"Has completado el juego. Tu puntuación es %s.","msgUncompletedActivity":"Actividad no completada","msgSuccessfulActivity":"Actividad superada. Puntuación: %s","msgUnsuccessfulActivity":"Actividad no superada. Puntuación: %s","msgTypeGame":"Arrastra","msgCheck":"Comprobar","msgRestart":"Reiniciar"}}&lt;/div&gt;&lt;a href="{{context_path}}/20251210172744694JD6//deforestacion.png" class="js-hidden dragdrop-LinkImages"&gt;0&lt;/a&gt;&lt;a href="{{context_path}}/20251210172744694JD6//contaminacion.png" class="js-hidden dragdrop-LinkImages"&gt;1&lt;/a&gt;&lt;a href="{{context_path}}/20251210172744694JD6//pesca_exesiva.png" class="js-hidden dragdrop-LinkImages"&gt;2&lt;/a&gt;&lt;a href="{{context_path}}/20251210172744694JD6//urbanizacion.png" class="js-hidden dragdrop-LinkImages"&gt;3&lt;/a&gt;&lt;div class="dragdrop-bns js-hidden"&gt;Su navegador no es compatible con esta herramienta.&lt;/div&gt;&lt;/div&gt;</htmlView><jsonProperties/><odeComponentsOrder>1</odeComponentsOrder><odeComponentsProperties><odeComponentsProperty><key>visibility</key><value>true</value></odeComponentsProperty><odeComponentsProperty><key>teacherOnly</key><value>false</value></odeComponentsProperty><odeComponentsProperty><key>identifier</key><value/></odeComponentsProperty><odeComponentsProperty><key>cssClass</key><value/></odeComponentsProperty></odeComponentsProperties></odeComponent></odeComponents></odePagStructure></odePagStructures></odeNavStructure></odeNavStructures></ode>
